freeplay_python_adk/__init__.py
freeplay_python_adk/client.py
freeplay_python_adk/constants.py
freeplay_python_adk/freeplay_llm_agent.py
freeplay_python_adk/freeplay_observability_plugin.py
freeplay_python_adk/py.typed
freeplay_python_adk/test_runs.py
freeplay_python_adk-0.2.2.dist-info/METADATA
freeplay_python_adk-0.2.2.dist-info/WHEEL
freeplay_python_adk-0.2.2.dist-info/RECORD
